[
  {
    "type": "article-journal",
    "id": "bWOcx5Cd",
    "author": [
      {
        "family": "Perkel",
        "given": "Jeffrey M."
      }
    ],
    "issued": {
      "date-parts": [
        [
          2019,
          8,
          19
        ]
      ]
    },
    "container-title": "Nature",
    "DOI": "10.1038/d41586-019-02477-9",
    "volume": "572",
    "issue": "7770",
    "page": "549-551",
    "publisher": "Springer Science and Business Media LLC",
    "title": "Starfish enterprise: finding RNA patterns in single cells",
    "URL": "https://doi.org/ggndkx",
    "PMID": "31427807",
    "note": "This CSL JSON Item was automatically generated by Manubot v0.3.1 using citation-by-identifier.\nstandard_id: doi:10.1038/d41586-019-02477-9"
  },
  {
    "type": "article-journal",
    "id": "HBp3QVVx",
    "author": [
      {
        "family": "Perkel",
        "given": "Jeffrey M."
      }
    ],
    "issued": {
      "date-parts": [
        [
          2019,
          9,
          2
        ]
      ]
    },
    "container-title": "Nature",
    "DOI": "10.1038/d41586-019-02619-z",
    "volume": "573",
    "issue": "7772",
    "page": "149-150",
    "publisher": "Springer Science and Business Media LLC",
    "title": "Workflow systems turn raw data into scientific knowledge",
    "URL": "https://doi.org/gf8nw9",
    "PMID": "31477884",
    "note": "This CSL JSON Item was automatically generated by Manubot v0.3.1 using citation-by-identifier.\nstandard_id: doi:10.1038/d41586-019-02619-z"
  },
  {
    "type": "article-journal",
    "id": "1GrjyqoH1",
    "author": [
      {
        "family": "Perkel",
        "given": "Jeffrey M."
      }
    ],
    "issued": {
      "date-parts": [
        [
          2019,
          11,
          5
        ]
      ]
    },
    "container-title": "Nature",
    "DOI": "10.1038/d41586-019-03366-x",
    "volume": "575",
    "issue": "7781",
    "page": "247-248",
    "publisher": "Springer Science and Business Media LLC",
    "title": "Make code accessible with these cloud services",
    "URL": "https://doi.org/ggnbfg",
    "PMID": "31690867",
    "note": "This CSL JSON Item was automatically generated by Manubot v0.3.1 using citation-by-identifier.\nstandard_id: doi:10.1038/d41586-019-03366-x"
  },
  {
    "type": "article-journal",
    "id": "KiqqECJ9",
    "author": [
      {
        "family": "Perkel",
        "given": "Jeffrey M."
      }
    ],
    "issued": {
      "date-parts": [
        [
          2019,
          11,
          26
        ]
      ]
    },
    "container-title": "Nature",
    "DOI": "10.1038/d41586-019-03632-y",
    "volume": "575",
    "issue": "7784",
    "page": "715-717",
    "publisher": "Springer Science and Business Media LLC",
    "title": "The microscope makers putting ever-larger biological samples under the spotlight",
    "URL": "https://doi.org/ggm9g5",
    "PMID": "31772373",
    "note": "This CSL JSON Item was automatically generated by Manubot v0.3.1 using citation-by-identifier.\nstandard_id: doi:10.1038/d41586-019-03632-y"
  },
  {
    "type": "article-journal",
    "id": "YuJbg3zO",
    "author": [
      {
        "family": "Himmelstein",
        "given": "Daniel S."
      },
      {
        "family": "Rubinetti",
        "given": "Vincent"
      },
      {
        "family": "Slochower",
        "given": "David R."
      },
      {
        "family": "Hu",
        "given": "Dongbo"
      },
      {
        "family": "Malladi",
        "given": "Venkat S."
      },
      {
        "family": "Greene",
        "given": "Casey S."
      },
      {
        "family": "Gitter",
        "given": "Anthony"
      }
    ],
    "issued": {
      "date-parts": [
        [
          2019,
          6,
          24
        ]
      ]
    },
    "container-title": "PLOS Computational Biology",
    "DOI": "10.1371/journal.pcbi.1007128",
    "volume": "15",
    "issue": "6",
    "page": "e1007128",
    "publisher": "Public Library of Science (PLoS)",
    "title": "Open collaborative writing with Manubot",
    "URL": "https://doi.org/c7np",
    "PMCID": "PMC6611653",
    "PMID": "31233491",
    "note": "This CSL JSON Item was automatically generated by Manubot v0.3.1 using citation-by-identifier.\nstandard_id: doi:10.1371/journal.pcbi.1007128"
  }
]
